werx-0.3.1.dist-info/METADATA
werx-0.3.1.dist-info/WHEEL
werx-0.3.1.dist-info/licenses/LICENSE
werx-0.3.1.dist-info/licenses/NOTICE
werx/__init__.py
werx/py.typed
werx/utils.py
werx/weighted_wer.py
werx/wer.py
werx/wer_analysis.py
werx/werx.cpython-311-x86_64-linux-gnu.so
werx-0.3.1.dist-info/RECORD
