Metadata-Version: 2.4
Name: werx
Version: 0.3.1
Classifier: Development Status :: 5 - Production/Stable
Classifier: License :: OSI Approved :: Apache Software License
Classifier: Programming Language :: Python :: 3
Classifier: Programming Language :: Python :: 3 :: Only
Classifier: Programming Language :: Python :: 3.10
Classifier: Programming Language :: Python :: 3.11
Classifier: Programming Language :: Python :: 3.12
Classifier: Programming Language :: Python :: 3.13
Classifier: Programming Language :: Python :: 3.14
Classifier: Programming Language :: Rust
Classifier: Programming Language :: Python :: Implementation :: CPython
Classifier: Operating System :: Microsoft :: Windows
Classifier: Operating System :: MacOS
Classifier: Operating System :: POSIX :: Linux
Classifier: Intended Audience :: Developers
Classifier: Topic :: Scientific/Engineering
Classifier: Topic :: Text Processing
Requires-Dist: maturin>=1.10.2 ; extra == 'dev'
Requires-Dist: pytest>=9.0.2 ; extra == 'dev'
Requires-Dist: mypy>=1.19.0 ; extra == 'dev'
Requires-Dist: ruff>=0.14.9 ; extra == 'dev'
Requires-Dist: polars>=1.36.1 ; extra == 'dataframes'
Requires-Dist: pandas>=2.3.3 ; extra == 'dataframes'
Requires-Dist: werpy>=3.1.0 ; extra == 'benchmarks'
Requires-Dist: jiwer>=4.0.0 ; extra == 'benchmarks'
Requires-Dist: pywer>=0.1.1 ; extra == 'benchmarks'
Requires-Dist: evaluate>=0.4.6 ; extra == 'benchmarks'
Requires-Dist: memory-profiler>=0.61.0 ; extra == 'benchmarks'
Requires-Dist: datasets>=4.4.1 ; extra == 'benchmarks'
Provides-Extra: dev
Provides-Extra: dataframes
Provides-Extra: benchmarks
License-File: LICENSE
License-File: NOTICE
Summary: A high-performance Python package for calculating Word Error Rate (WER), powered by Rust.
Keywords: werx,wer,word error rate,asr,automatic speech recognition,stt,speech-to-text,levenshtein distance,text similarity,nlp,accuracy metrics
Author-email: Ross Armstrong <ross.armstrong@analyticsinmotion.com>
Requires-Python: >=3.10
Project-URL: Repository, https://github.com/analyticsinmotion/werx
Project-URL: Bug Tracker, https://github.com/analyticsinmotion/werx/issues
